charts/__init__.py
charts/css.py
charts.css.py-0.4.0.dist-info/LICENSE
charts.css.py-0.4.0.dist-info/METADATA
charts.css.py-0.4.0.dist-info/WHEEL
charts.css.py-0.4.0.dist-info/entry_points.txt
charts.css.py-0.4.0.dist-info/top_level.txt
charts.css.py-0.4.0.dist-info/RECORD
