Metadata-Version: 2.1
Name: charts.css.py
Version: 0.4.0
Summary: charts.css.py brings charts.css to Python.
Home-page: https://github.com/rayluo/python-project-template
Author: Ray Luo
Author-email: rayluo.mba@gmail.com
License: MIT
Project-URL: Changelog, https://github.com/rayluo/python-project-template/releases
Keywords: chart,charts,charts.css,visualization,plot
Platform: UNKNOWN
Classifier: Development Status :: 4 - Beta
Classifier: License :: OSI Approved :: MIT License
Classifier: Operating System :: OS Independent
Classifier: Programming Language :: Python
Classifier: Programming Language :: Python :: 3
Classifier: Programming Language :: Python :: 3.6
Classifier: Programming Language :: Python :: 3.7
Classifier: Programming Language :: Python :: 3.8
Classifier: Programming Language :: Python :: 3.9
Classifier: Programming Language :: Python :: Implementation :: CPython
License-File: LICENSE
